slideflow/__init__.py
slideflow/_backend.py
slideflow/_version.py
slideflow/dataset.py
slideflow/errors.py
slideflow/heatmap.py
slideflow/mosaic.py
slideflow/plugin.py
slideflow/project.py
slideflow/project_utils.py
slideflow/sample_actions.py
slideflow/cellseg/__init__.py
slideflow/cellseg/seg_utils.py
slideflow/experimental/__init__.py
slideflow/experimental/embedding_search.py
slideflow/gan/__init__.py
slideflow/gan/interpolate.py
slideflow/gan/utils.py
slideflow/grad/__init__.py
slideflow/grad/plot_utils.py
slideflow/io/__init__.py
slideflow/io/gaussian.py
slideflow/io/io_utils.py
slideflow/io/tensorflow.py
slideflow/io/preservedsite/__init__.py
slideflow/io/preservedsite/crossfolds.py
slideflow/io/torch/__init__.py
slideflow/io/torch/augment.py
slideflow/io/torch/color.py
slideflow/io/torch/data_utils.py
slideflow/io/torch/dataloader.py
slideflow/io/torch/img_utils.py
slideflow/io/torch/indexed.py
slideflow/io/torch/iterable.py
slideflow/mil/__init__.py
slideflow/mil/_params.py
slideflow/mil/_registry.py
slideflow/mil/data.py
slideflow/mil/eval.py
slideflow/mil/features.py
slideflow/mil/utils.py
slideflow/mil/models/__init__.py
slideflow/mil/models/_utils.py
slideflow/mil/models/att_mil.py
slideflow/mil/models/transmil.py
slideflow/mil/models/bistro/__init__.py
slideflow/mil/models/bistro/model_utils.py
slideflow/mil/models/bistro/transformer.py
slideflow/mil/train/__init__.py
slideflow/mil/train/_fastai.py
slideflow/model/__init__.py
slideflow/model/adv_utils.py
slideflow/model/base.py
slideflow/model/features.py
slideflow/model/tensorflow.py
slideflow/model/tensorflow_utils.py
slideflow/model/torch.py
slideflow/model/torch_utils.py
slideflow/model/extractors/__init__.py
slideflow/model/extractors/_factory.py
slideflow/model/extractors/_factory_tensorflow.py
slideflow/model/extractors/_factory_torch.py
slideflow/model/extractors/_registry.py
slideflow/model/extractors/_tensorflow_base.py
slideflow/model/extractors/dinov2.py
slideflow-3.0.2.dist-info/LICENSE
slideflow-3.0.2.dist-info/METADATA
slideflow-3.0.2.dist-info/WHEEL
slideflow-3.0.2.dist-info/top_level.txt
slideflow-3.0.2.dist-info/RECORD
