Metadata-Version: 2.1
Name: slideflow
Version: 3.0.2
Summary: Deep learning tools for digital histology
Home-page: https://github.com/slideflow/slideflow
Author: James Dolezal
Author-email: james@slideflow.ai
Classifier: Programming Language :: Python :: 3
Classifier: License :: OSI Approved :: Apache Software License
Classifier: Operating System :: OS Independent
Requires-Python: >=3.7
License-File: LICENSE
Requires-Dist: gast >=0.3.3
Requires-Dist: scipy
Requires-Dist: scikit-learn
Requires-Dist: matplotlib >=3.2
Requires-Dist: imageio
Requires-Dist: opencv-python-headless
Requires-Dist: shapely
Requires-Dist: umap-learn
Requires-Dist: seaborn <0.14
Requires-Dist: pandas
Requires-Dist: pyvips
Requires-Dist: fpdf2
Requires-Dist: scikit-image
Requires-Dist: tqdm
Requires-Dist: click
Requires-Dist: protobuf <3.21
Requires-Dist: tensorboard
Requires-Dist: crc32c
Requires-Dist: numpy
Requires-Dist: tabulate
Requires-Dist: rasterio
Requires-Dist: smac ==1.4.0
Requires-Dist: ConfigSpace
Requires-Dist: rich
Requires-Dist: pillow >=6.0.0
Requires-Dist: imgui >=2.0.0
Requires-Dist: pyopengl
Requires-Dist: glfw
Requires-Dist: saliency
Requires-Dist: pyperclip
Requires-Dist: requests
Requires-Dist: parameterized
Requires-Dist: zarr
Requires-Dist: gdown
Requires-Dist: triangle
Requires-Dist: pyarrow
Provides-Extra: all
Requires-Dist: cellpose <2.2 ; extra == 'all'
Requires-Dist: cucim ; extra == 'all'
Requires-Dist: sphinx ; extra == 'all'
Requires-Dist: sphinx-markdown-tables ; extra == 'all'
Requires-Dist: sphinxcontrib-video ; extra == 'all'
Requires-Dist: pygments-csv-lexer ; extra == 'all'
Requires-Dist: torch ; extra == 'all'
Requires-Dist: torchvision ; extra == 'all'
Requires-Dist: spacy <3.8 ; extra == 'all'
Requires-Dist: fastai ; extra == 'all'
Requires-Dist: pretrainedmodels ; extra == 'all'
Requires-Dist: tensorflow <2.12,>=2.7 ; extra == 'all'
Requires-Dist: tensorflow-probability <0.20 ; extra == 'all'
Requires-Dist: tensorflow-datasets ; extra == 'all'
Provides-Extra: cellpose
Requires-Dist: cellpose <2.2 ; extra == 'cellpose'
Provides-Extra: cucim
Requires-Dist: cucim ; extra == 'cucim'
Provides-Extra: dev
Requires-Dist: sphinx ; extra == 'dev'
Requires-Dist: sphinx-markdown-tables ; extra == 'dev'
Requires-Dist: sphinxcontrib-video ; extra == 'dev'
Requires-Dist: pygments-csv-lexer ; extra == 'dev'
Provides-Extra: tf
Requires-Dist: tensorflow <2.12,>=2.7 ; extra == 'tf'
Requires-Dist: tensorflow-probability <0.20 ; extra == 'tf'
Requires-Dist: tensorflow-datasets <4.9.0 ; extra == 'tf'
Provides-Extra: torch
Requires-Dist: torch ; extra == 'torch'
Requires-Dist: torchvision ; extra == 'torch'
Requires-Dist: pretrainedmodels ; extra == 'torch'
Requires-Dist: cellpose <2.2 ; extra == 'torch'
Requires-Dist: spacy <3.8 ; extra == 'torch'
Requires-Dist: fastai ; extra == 'torch'
Requires-Dist: pytorch-lightning ; extra == 'torch'
Requires-Dist: timm ; extra == 'torch'
Requires-Dist: segmentation-models-pytorch ; extra == 'torch'
